{"_ts":[1501625325,1501669215,1501756962,1501800718,1501844979,1501888700,1501932014,1502019929],"_r":{"breakdown":{"html":{"bytes":[13782,13786,13794,13761,13794,13885,13810,13787],"requests":[7,7,7,7,7,7,7,7]},"js":{"bytes":[194535,195020,194950,195028,195833,195879,196169,196507],"requests":[16,16,16,16,16,16,16,16]},"css":{"bytes":[14897,14897,14897,14897,14897,14897,14897,14897],"requests":[1,1,1,1,1,1,1,1]},"image":{"bytes":[18559,18561,18563,18671,18561,18562,18562,18563],"requests":[12,12,12,13,12,12,12,12]},"flash":{"bytes":[0,0,0,0,0,0,0,0],"requests":[0,0,0,0,0,0,0,0]},"font":{"bytes":[0,0,0,0,0,0,0,0],"requests":[0,0,0,0,0,0,0,0]},"other":{"bytes":[796,962,796,796,796,796,796,796],"requests":[1,2,1,1,1,1,1,1]}},"date":[1501625325,1501669215,1501756962,1501800718,1501844979,1501888700,1501932014,1502019929],"domElements":[240,240,240,240,240,240,240,240],"domInteractive":[766,618,719,972,804,2193,962,1026],"firstPaint":[1167,967,1118,965,1220,2161,937,1013],"fullyLoaded":[4032,3742,3770,3916,3946,6014,4268,3886],"id":["170801_DE_1JFG","170802_6M_RSW","170803_SS_1A06","170803_9P_29XG","170804_7Z_YND","170804_NN_1W7M","170805_W9_MSW","170806_4D_KE0"],"loadTime":[3358,3127,3305,3358,3389,5508,3749,3411],"render":[1464,1256,1555,1279,1670,2870,1439,1381],"SpeedIndex":[1633,1469,1769,1505,1875,3086,1684,1548],"TTFB":[437,300,329,350,391,1162,349,395],"videoFrames":[[{"_i":"frame_0000.jpg","_t":0,"_vc":0},{"_i":"frame_0015.jpg","_t":1500,"_vc":72},{"_i":"frame_0016.jpg","_t":1600,"_vc":93},{"_i":"frame_0018.jpg","_t":1800,"_vc":93},{"_i":"frame_0019.jpg","_t":1900,"_vc":93},{"_i":"frame_0020.jpg","_t":2000,"_vc":93},{"_i":"frame_0021.jpg","_t":2100,"_vc":93},{"_i":"frame_0024.jpg","_t":2400,"_vc":93},{"_i":"frame_0025.jpg","_t":2500,"_vc":93},{"_i":"frame_0027.jpg","_t":2700,"_vc":93},{"_i":"frame_0028.jpg","_t":2800,"_vc":93},{"_i":"frame_0029.jpg","_t":2900,"_vc":93},{"_i":"frame_0031.jpg","_t":3100,"_vc":100}],[{"_i":"frame_0000.jpg","_t":0,"_vc":0},{"_i":"frame_0013.jpg","_t":1300,"_vc":71},{"_i":"frame_0014.jpg","_t":1400,"_vc":93},{"_i":"frame_0016.jpg","_t":1600,"_vc":93},{"_i":"frame_0018.jpg","_t":1800,"_vc":93},{"_i":"frame_0020.jpg","_t":2000,"_vc":93},{"_i":"frame_0022.jpg","_t":2200,"_vc":93},{"_i":"frame_0024.jpg","_t":2400,"_vc":93},{"_i":"frame_0026.jpg","_t":2600,"_vc":93},{"_i":"frame_0028.jpg","_t":2800,"_vc":93},{"_i":"frame_0030.jpg","_t":3000,"_vc":93},{"_i":"frame_0032.jpg","_t":3200,"_vc":93},{"_i":"frame_0034.jpg","_t":3400,"_vc":100}],[{"_i":"frame_0000.jpg","_t":0,"_vc":0},{"_i":"frame_0016.jpg","_t":1600,"_vc":71},{"_i":"frame_0017.jpg","_t":1700,"_vc":93},{"_i":"frame_0018.jpg","_t":1800,"_vc":93},{"_i":"frame_0019.jpg","_t":1900,"_vc":93},{"_i":"frame_0020.jpg","_t":2000,"_vc":93},{"_i":"frame_0023.jpg","_t":2300,"_vc":93},{"_i":"frame_0025.jpg","_t":2500,"_vc":93},{"_i":"frame_0027.jpg","_t":2700,"_vc":93},{"_i":"frame_0029.jpg","_t":2900,"_vc":93},{"_i":"frame_0031.jpg","_t":3100,"_vc":93},{"_i":"frame_0033.jpg","_t":3300,"_vc":93},{"_i":"frame_0035.jpg","_t":3500,"_vc":93},{"_i":"frame_0037.jpg","_t":3700,"_vc":100}],[{"_i":"frame_0000.jpg","_t":0,"_vc":0},{"_i":"frame_0013.jpg","_t":1300,"_vc":71},{"_i":"frame_0015.jpg","_t":1500,"_vc":93},{"_i":"frame_0016.jpg","_t":1600,"_vc":93},{"_i":"frame_0018.jpg","_t":1800,"_vc":93},{"_i":"frame_0020.jpg","_t":2000,"_vc":93},{"_i":"frame_0022.jpg","_t":2200,"_vc":93},{"_i":"frame_0023.jpg","_t":2300,"_vc":93},{"_i":"frame_0025.jpg","_t":2500,"_vc":93},{"_i":"frame_0027.jpg","_t":2700,"_vc":93},{"_i":"frame_0028.jpg","_t":2800,"_vc":93},{"_i":"frame_0030.jpg","_t":3000,"_vc":93},{"_i":"frame_0032.jpg","_t":3200,"_vc":93},{"_i":"frame_0034.jpg","_t":3400,"_vc":93},{"_i":"frame_0036.jpg","_t":3600,"_vc":100}],[{"_i":"frame_0000.jpg","_t":0,"_vc":0},{"_i":"frame_0017.jpg","_t":1700,"_vc":72},{"_i":"frame_0019.jpg","_t":1900,"_vc":93},{"_i":"frame_0020.jpg","_t":2000,"_vc":93},{"_i":"frame_0022.jpg","_t":2200,"_vc":93},{"_i":"frame_0024.jpg","_t":2400,"_vc":93},{"_i":"frame_0027.jpg","_t":2700,"_vc":93},{"_i":"frame_0028.jpg","_t":2800,"_vc":93},{"_i":"frame_0031.jpg","_t":3100,"_vc":93},{"_i":"frame_0033.jpg","_t":3300,"_vc":93},{"_i":"frame_0034.jpg","_t":3400,"_vc":93},{"_i":"frame_0036.jpg","_t":3600,"_vc":100}],[{"_i":"frame_0000.jpg","_t":0,"_vc":0},{"_i":"frame_0029.jpg","_t":2900,"_vc":71},{"_i":"frame_0030.jpg","_t":3000,"_vc":81},{"_i":"frame_0032.jpg","_t":3200,"_vc":93},{"_i":"frame_0033.jpg","_t":3300,"_vc":93},{"_i":"frame_0035.jpg","_t":3500,"_vc":93},{"_i":"frame_0036.jpg","_t":3600,"_vc":93},{"_i":"frame_0037.jpg","_t":3700,"_vc":93},{"_i":"frame_0038.jpg","_t":3800,"_vc":93},{"_i":"frame_0040.jpg","_t":4000,"_vc":93},{"_i":"frame_0042.jpg","_t":4200,"_vc":93},{"_i":"frame_0044.jpg","_t":4400,"_vc":93},{"_i":"frame_0045.jpg","_t":4500,"_vc":93},{"_i":"frame_0047.jpg","_t":4700,"_vc":93},{"_i":"frame_0049.jpg","_t":4900,"_vc":100}],[{"_i":"frame_0000.jpg","_t":0,"_vc":0},{"_i":"frame_0014.jpg","_t":1400,"_vc":73},{"_i":"frame_0018.jpg","_t":1800,"_vc":82},{"_i":"frame_0020.jpg","_t":2000,"_vc":93},{"_i":"frame_0021.jpg","_t":2100,"_vc":93},{"_i":"frame_0024.jpg","_t":2400,"_vc":93},{"_i":"frame_0027.jpg","_t":2700,"_vc":93},{"_i":"frame_0031.jpg","_t":3100,"_vc":93},{"_i":"frame_0032.jpg","_t":3200,"_vc":93},{"_i":"frame_0034.jpg","_t":3400,"_vc":93},{"_i":"frame_0036.jpg","_t":3600,"_vc":93},{"_i":"frame_0038.jpg","_t":3800,"_vc":93},{"_i":"frame_0040.jpg","_t":4000,"_vc":100}],[{"_i":"frame_0000.jpg","_t":0,"_vc":0},{"_i":"frame_0014.jpg","_t":1400,"_vc":71},{"_i":"frame_0015.jpg","_t":1500,"_vc":93},{"_i":"frame_0016.jpg","_t":1600,"_vc":93},{"_i":"frame_0019.jpg","_t":1900,"_vc":93},{"_i":"frame_0020.jpg","_t":2000,"_vc":93},{"_i":"frame_0022.jpg","_t":2200,"_vc":93},{"_i":"frame_0024.jpg","_t":2400,"_vc":93},{"_i":"frame_0026.jpg","_t":2600,"_vc":93},{"_i":"frame_0027.jpg","_t":2700,"_vc":93},{"_i":"frame_0028.jpg","_t":2800,"_vc":93},{"_i":"frame_0030.jpg","_t":3000,"_vc":93},{"_i":"frame_0032.jpg","_t":3200,"_vc":100}]],"visualComplete":[3100,3400,3700,3600,3600,4900,4000,3200],"lighthouse":[null,null,null,null,null,null,null,null],"pagespeed":[87,87,87,87,87,86,87,87]}}